{
    "common": {
        "name": "mobile",
        "version": "0.5.0",
        "news": {
            "0.5.0": {
                "en": "The multilingual names were fixed",
                "de": "Die mehrsprachigen Namen wurden korrigiert",
                "ru": "Многоязычные имена были исправлены",
                "pt": "Os nomes multilíngües foram corrigidos",
                "nl": "De meertalige namen werden vastgesteld",
                "fr": "Les noms multilingues ont été corrigés",
                "it": "I nomi multilingue sono stati corretti",
                "es": "Los nombres multilingües fueron arreglados.",
                "pl": "Wielojęzyczne nazwy zostały naprawione",
                "zh-cn": "多语种名称是固定的"
            },
            "0.4.12": {
                "en": "Update adapter type",
                "de": "Update Adaptertyp",
                "ru": "Обновить тип драйвера"
            },
            "0.4.11": {
                "en": "Fixed blind states",
                "de": "Rolladenstatus korrigiert",
                "ru": "Исправлены слепые состояния"
            },
            "0.4.10": {
                "en": "Better support of cloud",
                "de": "Bessere cloud Unterstützung",
                "ru": "Поддержка облака"
            },
            "0.4.9": {
                "en": "Fix rooms rendering\nadd green, red, blue, white types",
                "de": "Korrigiere Räumeaufbau\nHinzugefügt: rot, blau, grün- Typen",
                "ru": "Исправлено построение комнат\nДобавлены новые типы: красный, синий..."
            },
            "0.4.8": {
                "en": "implement type blind",
                "de": "Typ Rolladen ist fertig",
                "ru": "Добавлен тип жалюзи"
            },
            "0.4.7": {
                "en": "fix input number and select value",
                "de": "Korrigieren Nummereingabe und Wertauswahl",
                "ru": "исправить ввод номера и выбор значения"
            },
            "0.4.6": {
                "en": "fix input number and select value",
                "de": "Korrigieren Nummereingabe und Wertauswahl",
                "ru": "исправить ввод номера и выбор значения"
            }
        },
        "title": "Mobile UI",
        "desc": {
            "en": "jQuery Mobile based ioBroker user interface",
            "de": "ioBroker GUI für mobile Geräte",
            "ru": "ioBroker визуализация для мобильных устройств",
            "pt": "Interface de usuário do ioBroker baseada em jQuery Mobile",
            "nl": "jQuery Mobiel gebaseerde ioBroker gebruikersinterface",
            "fr": "Interface utilisateur ioBroker basée sur jQuery Mobile",
            "it": "Interfaccia utente ioBroker basata su jQuery Mobile",
            "es": "Interfaz de usuario ioBroker basada en jQuery Mobile",
            "pl": "Interfejs użytkownika ioBroker oparty na jQuery Mobile",
            "zh-cn": "基于jQuery Mobile的ioBroker用户界面"
        },
        "platform": "javascript/Node.js",
        "onlyWWW": "true",
        "loglevel": "info",
        "dependencies": [
            "web"
        ],
        "icon": "mobile.png",
        "extIcon": "https://raw.githubusercontent.com/ioBroker/ioBroker.mobile/master/admin/mobile.png",
        "keywords": [
            "user",
            "interface",
            "webapp",
            "jquerymobile",
            "ui"
        ],
        "readme": "https://github.com/ioBroker/ioBroker.mobile/blob/master/README.md",
        "singleton": true,
        "preserveSettings": "mobile",
        "authors": [
            "bluefox <dogafox@gmail.com>"
        ],
        "localLink": "%web_protocol%://%ip%:%web_port%/mobile/index.html",
        "type": "visualization",
        "license": "MIT",
        "noConfig": true,
        "welcomeScreen": {
            "link": "mobile/index.html",
            "name": "mobile",
            "img": "mobile.admin/mobile.png",
            "color": "black",
            "order": 2
        }
    },
    "native": {
        "root": [
            "enum.favorites.Admin",
            "enum.rooms",
            "enum.functions"
        ],
        "swatches": {
            "header": "b",
            "content": "c",
            "footer": "a"
        }
    },
    "objects": []
}